{"Rk": {"0": "1", "1": "2", "2": "3", "3": "4", "4": "5", "7": "6", "8": "7", "9": "8", "10": "9", "11": "10", "12": "11", "13": "12", "14": "13", "15": "14", "16": "15", "17": "16", "18": "17", "19": "18", "20": "19", "21": "20", "23": "21", "24": "22", "25": "23", "26": "24", "27": "25", "28": "26", "29": "27", "30": "28", "33": "29", "34": "30", "35": "31", "36": "32", "37": "33", "38": "34", "39": "35", "40": "36", "41": "37", "42": "38", "43": "39", "46": "40", "48": "41", "49": "42", "50": "43", "51": "44", "54": "45", "55": "46", "56": "47", "57": "48", "58": "49", "59": "50", "62": "51", "63": "52", "64": "53", "65": "54", "66": "55", "67": "56", "68": "57", "69": "58", "72": "59", "73": "60", "75": "61", "76": "62", "77": "63", "78": "64", "79": "65", "80": "66", "81": "67", "82": "68", "83": "69", "84": "70", "87": "71", "88": "72", "89": "73", "90": "74", "93": "75", "94": "76", "95": "77", "96": "78", "97": "79", "98": "80", "100": "81", "101": "82", "102": "83", "103": "84", "106": "85", "107": "86", "108": "87", "109": "88", "110": "89", "111": "90", "114": "91", "115": "92", "116": "93", "117": "94", "118": "95", "119": "96", "122": "97", "123": "98", "124": "99", "125": "100", "127": "101", "128": "102", "129": "103", "130": "104", "131": "105", "132": "106", "133": "107", "134": "108", "135": "109", "139": "110"}, "Player": {"0": "Don Ackerman", "1": "Don Asmonga", "2": "Jim Baechtold", "3": "Don Barksdale*", "4": "Leo Barnhorst", "7": "Ernie Barrett", "8": "Ernie Beck", "9": "Irv Bemoras", "10": "Bill Bolger", "11": "Vince Boryla", "12": "Bob Brannum", "13": "Carl Braun*", "14": "Frankie Brian", "15": "Bill Calhoun", "16": "Cal Christensen", "17": "Nat Clifton*", "18": "Jack Coleman", "19": "Chuck Cooper*", "20": "Bob Cousy*", "21": "Bob Davies*", "23": "Walt Davis", "24": "Bob Donham", "25": "Gene Dyker", "26": "Ed Earle", "27": "Ray Felix", "28": "Danny Finn", "29": "Larry Foust", "30": "Jim Fritsche", "33": "Joe Fulks*", "34": "Bill Gabor", "35": "Harry Gallatin*", "36": "Jack George", "37": "Bato Govedarica", "38": "Joe Graboski", "39": "Norm Grekin", "40": "Alex Hannum*", "41": "Rollen Hans", "42": "Bob Harris", "43": "Bob Harrison", "46": "Lew Hitch", "48": "Paul Hoffman", "49": "Jim Holstein", "50": "Red Holzman*", "51": "Bob Houbregs*", "54": "Mel Hutchins", "55": "Neil Johnston*", "56": "Billy Kenville", "57": "George King", "58": "Dick Knostman", "59": "Bob Lavoy", "62": "Earl Lloyd*", "63": "Don Lofgran", "64": "Clyde Lovellette*", "65": "Jim Luisi", "66": "Ed Macauley*", "67": "Mo Mahoney", "68": "Slater Martin*", "69": "Al Masino", "72": "Alfred McGuire*", "73": "Dick McGuire*", "75": "Jack McMahon", "76": "Monk Meineke", "77": "Ed Mikan", "78": "George Mikan*", "79": "Vern Mikkelsen*", "80": "Eddie Miller", "81": "Jack Molinas", "82": "Ken Murray", "83": "Jim Neal", "84": "Jack Nichols", "87": "Paul Nolen", "88": "Mike Novak", "89": "Wally Osterkorn", "90": "Bob Peterson", "93": "James Phelan", "94": "Andy Phillip*", "95": "Jim Pollard*", "96": "George Ratkovicz", "97": "Connie Rea", "98": "Frank Reddout", "100": "Arnie Risen*", "101": "Al Roges", "102": "Pep Saul", "103": "Fred Schaus", "106": "Dolph Schayes*", "107": "Dick Schnittker", "108": "Fred Scolari", "109": "George Senesky", "110": "Paul Seymour", "111": "Chuck Share", "114": "Bill Sharman*", "115": "Connie Simmons", "116": "Zeke Sinicola", "117": "Whitey Skoog", "118": "Ed Smith", "119": "Joe Smyth", "122": "Odie Spears", "123": "Don Sunderlage", "124": "Dick Surhoff", "125": "Norm Swanson", "127": "Bill Tosheff", "128": "Hal Uplinger", "129": "Ernie Vandeweghe", "130": "Paul Walther", "131": "Isaac Walthour", "132": "Bobby Wanzer*", "133": "Mark Workman", "134": "George Yardley*", "135": "Max Zaslofsky", "139": "Zeke Zawoluk"}, "Pos": {"0": "PG", "1": "G", "2": "SF", "3": "PF", "4": "F-G", "7": "SG", "8": "SG", "9": "SF", "10": "SF", "11": "SF", "12": "PF", "13": "SG", "14": "SG", "15": "SF", "16": "SF", "17": "PF", "18": "PF", "19": "SF", "20": "PG", "21": "PG", "23": "PF", "24": "SG", "25": "F", "26": "PF", "27": "C", "28": "PG", "29": "C", "30": "PF", "33": "PF", "34": "SG", "35": "PF", "36": "PG", "37": "PG", "38": "PF", "39": "F", "40": "PF", "41": "SG", "42": "SF", "43": "SG", "46": "PF", "48": "PG", "49": "SF", "50": "PG", "51": "PF", "54": "PF", "55": "C", "56": "PG", "57": "PG", "58": "C", "59": "PF", "62": "SF", "63": "SF", "64": "C", "65": "PG", "66": "C", "67": "F", "68": "PG", "69": "PG", "72": "PG", "73": "PG", "75": "PG", "76": "PF", "77": "C", "78": "C", "79": "PF", "80": "C", "81": "SF", "82": "SG", "83": "C", "84": "C-F", "87": "C", "88": "PF", "89": "PF", "90": "F", "93": "G", "94": "PG", "95": "SF", "96": "PF", "97": "G-F", "98": "F", "100": "C", "101": "SF", "102": "SG", "103": "SF", "106": "C", "107": "SF", "108": "PG", "109": "PG", "110": "SG", "111": "C", "114": "SG", "115": "C", "116": "G", "117": "SG", "118": "SF", "119": "SF", "122": "SF", "123": "SG", "124": "PF", "125": "SF", "127": "PG", "128": "SG", "129": "SG", "130": "SG", "131": "G", "132": "SG", "133": "F-C", "134": "SF", "135": "SG", "139": "SF"}, "Age": {"0": "23", "1": "25", "2": "26", "3": "30", "4": "29", "7": "24", "8": "22", "9": "23", "10": "22", "11": "26", "12": "28", "13": "26", "14": "30", "15": "26", "16": "26", "17": "31", "18": "29", "19": "27", "20": "25", "21": "34", "23": "23", "24": "27", "25": "23", "26": "26", "27": "23", "28": "25", "29": "25", "30": "22", "33": "32", "34": "31", "35": "26", "36": "25", "37": "25", "38": "24", "39": "23", "40": "30", "41": "22", "42": "26", "43": "26", "46": "24", "48": "28", "49": "23", "50": "33", "51": "21", "54": "25", "55": "24", "56": "23", "57": "25", "58": "22", "59": "27", "62": "25", "63": "24", "64": "24", "65": "25", "66": "25", "67": "26", "68": "28", "69": "25", "72": "25", "73": "28", "75": "25", "76": "23", "77": "28", "78": "29", "79": "25", "80": "22", "81": "22", "82": "25", "83": "23", "84": "27", "87": "24", "88": "38", "89": "25", "90": "22", "93": "24", "94": "31", "95": "31", "96": "31", "97": "19", "98": NaN, "100": "29", "101": "23", "102": "29", "103": "28", "106": "25", "107": "25", "108": "31", "109": "31", "110": "26", "111": "26", "114": "27", "115": "28", "116": "25", "117": "27", "118": "24", "119": "24", "122": "29", "123": "24", "124": "24", "125": "23", "127": "27", "128": "24", "129": "25", "130": "26", "131": "23", "132": "32", "133": "23", "134": "25", "135": "28", "139": "23"}, "Tm": {"0": "NYK", "1": "BLB", "2": "NYK", "3": "BOS", "4": "TOT", "7": "BOS", "8": "PHW", "9": "MLH", "10": "BLB", "11": "NYK", "12": "BOS", "13": "NYK", "14": "FTW", "15": "MLH", "16": "ROC", "17": "NYK", "18": "ROC", "19": "BOS", "20": "BOS", "21": "ROC", "23": "PHW", "24": "BOS", "25": "MLH", "26": "SYR", "27": "BLB", "28": "PHW", "29": "FTW", "30": "TOT", "33": "PHW", "34": "SYR", "35": "NYK", "36": "PHW", "37": "SYR", "38": "PHW", "39": "PHW", "40": "ROC", "41": "BLB", "42": "BOS", "43": "TOT", "46": "MLH", "48": "BLB", "49": "MNL", "50": "MLH", "51": "TOT", "54": "FTW", "55": "PHW", "56": "SYR", "57": "SYR", "58": "SYR", "59": "TOT", "62": "SYR", "63": "MLH", "64": "MNL", "65": "BLB", "66": "BOS", "67": "BLB", "68": "MNL", "69": "TOT", "72": "NYK", "73": "NYK", "75": "ROC", "76": "FTW", "77": "BOS", "78": "MNL", "79": "MNL", "80": "BLB", "81": "FTW", "82": "FTW", "83": "SYR", "84": "TOT", "87": "BLB", "88": "SYR", "89": "SYR", "90": "TOT", "93": "PHW", "94": "FTW", "95": "MNL", "96": "MLH", "97": "BLB", "98": "ROC", "100": "ROC", "101": "BLB", "102": "MNL", "103": "TOT", "106": "SYR", "107": "MNL", "108": "FTW", "109": "PHW", "110": "SYR", "111": "TOT", "114": "BOS", "115": "NYK", "116": "FTW", "117": "MNL", "118": "NYK", "119": "TOT", "122": "ROC", "123": "MLH", "124": "MLH", "125": "ROC", "127": "MLH", "128": "BLB", "129": "NYK", "130": "PHW", "131": "MLH", "132": "ROC", "133": "BLB", "134": "FTW", "135": "TOT", "139": "PHW"}, "G": {"0": "28", "1": "7", "2": "70", "3": "63", "4": "72", "7": "59", "8": "15", "9": "69", "10": "20", "11": "52", "12": "71", "13": "72", "14": "64", "15": "72", "16": "70", "17": "72", "18": "71", "19": "70", "20": "72", "21": "72", "23": "68", "24": "68", "25": "11", "26": "2", "27": "72", "28": "68", "29": "72", "30": "68", "33": "61", "34": "61", "35": "72", "36": "71", "37": "23", "38": "71", "39": "1", "40": "72", "41": "67", "42": "71", "43": "64", "46": "72", "48": "72", "49": "70", "50": "51", "51": "70", "54": "72", "55": "72", "56": "72", "57": "72", "58": "5", "59": "68", "62": "72", "63": "21", "64": "72", "65": "31", "66": "71", "67": "2", "68": "69", "69": "27", "72": "64", "73": "68", "75": "71", "76": "71", "77": "9", "78": "72", "79": "72", "80": "72", "81": "32", "82": "49", "83": "67", "84": "75", "87": "1", "88": "5", "89": "70", "90": "8", "93": "4", "94": "71", "95": "71", "96": "69", "97": "20", "98": "7", "100": "72", "101": "67", "102": "71", "103": "67", "106": "72", "107": "71", "108": "64", "109": "58", "110": "71", "111": "68", "114": "72", "115": "72", "116": "9", "117": "71", "118": "12", "119": "40", "122": "72", "123": "68", "124": "32", "125": "63", "127": "71", "128": "23", "129": "15", "130": "64", "131": "4", "132": "72", "133": "14", "134": "63", "135": "65", "139": "71"}, "MP": {"0": "220", "1": "46", "2": "1627", "3": "1358", "4": "2064", "7": "641", "8": "422", "9": "1496", "10": "202", "11": "1522", "12": "1729", "13": "2373", "14": "973", "15": "2370", "16": "1654", "17": "2179", "18": "2377", "19": "1101", "20": "2857", "21": "2137", "23": "1568", "24": "1451", "25": "91", "26": "12", "27": "2672", "28": "1562", "29": "2693", "30": "1221", "33": "501", "34": "1211", "35": "2690", "36": "2648", "37": "258", "38": "2759", "39": "1", "40": "1707", "41": "1556", "42": "1898", "43": "1443", "46": "2452", "48": "2505", "49": "1155", "50": "649", "51": "1970", "54": "2934", "55": "3296", "56": "1405", "57": "2370", "58": "47", "59": "1277", "62": "2206", "63": "380", "64": "1255", "65": "367", "66": "2792", "67": "11", "68": "2472", "69": "181", "72": "849", "73": "2343", "75": "1891", "76": "1466", "77": "71", "78": "2362", "79": "2247", "80": "1657", "81": "958", "82": "528", "83": "899", "84": "1607", "87": "2", "88": "24", "89": "2164", "90": "60", "93": "33", "94": "2705", "95": "2483", "96": "2170", "97": "154", "98": "18", "100": "2385", "101": "1937", "102": "1805", "103": "1515", "106": "2655", "107": "1040", "108": "1589", "109": "771", "110": "2727", "111": "1576", "114": "2467", "115": "2006", "116": "33", "117": "1877", "118": "127", "119": "495", "122": "1633", "123": "2232", "124": "358", "125": "611", "127": "1825", "128": "268", "129": "271", "130": "2067", "131": "30", "132": "2538", "133": "151", "134": "1489", "135": "1881", "139": "1795"}, "PER": {"0": "1.0", "1": "-7.5", "2": "10.5", "3": "14.2", "4": NaN, "7": "4.7", "8": "8.1", "9": "12.7", "10": "10.7", "11": "6.8", "12": "10.5", "13": "17.8", "14": "15.6", "15": "12.5", "16": "11.7", "17": "14.8", "18": "14.8", "19": "9.6", "20": "21.0", "21": "18.0", "23": "11.2", "24": "13.6", "25": "0.4", "26": "15.0", "27": "22.9", "28": "13.9", "29": "22.8", "30": "7.8", "33": "3.7", "34": "14.6", "35": "24.1", "36": "12.1", "37": "7.1", "38": "14.5", "39": "-23.3", "40": "9.5", "41": "11.5", "42": "11.0", "43": "7.5", "46": "14.9", "48": "13.5", "49": "7.9", "50": "10.2", "51": "13.4", "54": "14.6", "55": "25.6", "56": "14.5", "57": "14.5", "58": "17.4", "59": "12.5", "62": "12.4", "63": "10.9", "64": "20.7", "65": "7.6", "66": "23.4", "67": "0.6", "68": "12.0", "69": "17.1", "72": "8.0", "73": "16.0", "75": "14.9", "76": "13.1", "77": "8.2", "78": "28.7", "79": "16.5", "80": "21.3", "81": "19.2", "82": "7.9", "83": "9.9", "84": NaN, "87": "-20.3", "88": "-14.6", "89": "12.6", "90": "10.8", "93": "-4.8", "94": "16.0", "95": "15.9", "96": "15.3", "97": "4.4", "98": "42.5", "100": "18.2", "101": "10.6", "102": "9.7", "103": "14.3", "106": "24.3", "107": "11.9", "108": "9.8", "109": "7.3", "110": "16.2", "111": "20.1", "114": "18.6", "115": "14.8", "116": "-1.7", "117": "11.3", "118": "8.5", "119": "11.9", "122": "14.2", "123": "12.4", "124": "14.4", "125": "4.0", "127": "9.1", "128": "10.7", "129": "11.7", "130": "10.8", "131": "-5.4", "132": "17.8", "133": "12.8", "134": "19.5", "135": "15.3", "139": "13.7"}, "TS%": {"0": ".285", "1": ".162", "2": ".437", "3": ".448", "4": ".368", "7": ".332", "8": ".348", "9": ".427", "10": ".433", "11": ".375", "12": ".376", "13": ".495", "14": ".464", "15": ".441", "16": ".404", "17": ".419", "18": ".432", "19": ".375", "20": ".464", "21": ".458", "23": ".399", "24": ".489", "25": ".271", "26": ".532", "27": ".491", "28": ".401", "29": ".483", "30": ".344", "33": ".299", "34": ".430", "35": ".538", "36": ".396", "37": ".394", "38": ".409", "39": NaN, "40": ".393", "41": ".406", "42": ".433", "43": ".368", "46": ".414", "48": ".404", "49": ".356", "50": ".383", "51": ".448", "54": ".444", "55": ".531", "56": ".464", "57": ".442", "58": ".438", "59": ".441", "62": ".431", "63": ".382", "64": ".465", "65": ".394", "66": ".563", "67": ".000", "68": ".449", "69": ".491", "72": ".369", "73": ".482", "75": ".431", "76": ".434", "77": ".376", "78": ".466", "79": ".442", "80": ".486", "81": ".494", "82": ".336", "83": ".365", "84": ".369", "87": ".000", "88": ".063", "89": ".413", "90": ".505", "93": ".174", "94": ".455", "95": ".423", "96": ".459", "97": ".230", "98": ".838", "100": ".447", "101": ".411", "102": ".417", "103": ".474", "106": ".498", "107": ".452", "108": ".405", "109": ".390", "110": ".466", "111": ".459", "114": ".531", "115": ".425", "116": ".295", "117": ".433", "118": ".320", "119": ".393", "122": ".452", "123": ".424", "124": ".426", "125": ".303", "127": ".367", "128": ".415", "129": ".424", "130": ".436", "131": ".167", "132": ".468", "133": ".435", "134": ".484", "135": ".444", "139": ".462"}, "3PAr": {"0": NaN, "1": NaN, "2": NaN, "3": NaN, "4": NaN, "7": NaN, "8": NaN, "9": NaN, "10": NaN, "11": NaN, "12": NaN, "13": NaN, "14": NaN, "15": NaN, "16": NaN, "17": NaN, "18": NaN, "19": NaN, "20": NaN, "21": NaN, "23": NaN, "24": NaN, "25": NaN, "26": NaN, "27": NaN, "28": NaN, "29": NaN, "30": NaN, "33": NaN, "34": NaN, "35": NaN, "36": NaN, "37": NaN, "38": NaN, "39": NaN, "40": NaN, "41": NaN, "42": NaN, "43": NaN, "46": NaN, "48": NaN, "49": NaN, "50": NaN, "51": NaN, "54": NaN, "55": NaN, "56": NaN, "57": NaN, "58": NaN, "59": NaN, "62": NaN, "63": NaN, "64": NaN, "65": NaN, "66": NaN, "67": NaN, "68": NaN, "69": NaN, "72": NaN, "73": NaN, "75": NaN, "76": NaN, "77": NaN, "78": NaN, "79": NaN, "80": NaN, "81": NaN, "82": NaN, "83": NaN, "84": NaN, "87": NaN, "88": NaN, "89": NaN, "90": NaN, "93": NaN, "94": NaN, "95": NaN, "96": NaN, "97": NaN, "98": NaN, "100": NaN, "101": NaN, "102": NaN, "103": NaN, "106": NaN, "107": NaN, "108": NaN, "109": NaN, "110": NaN, "111": NaN, "114": NaN, "115": NaN, "116": NaN, "117": NaN, "118": NaN, "119": NaN, "122": NaN, "123": NaN, "124": NaN, "125": NaN, "127": NaN, "128": NaN, "129": NaN, "130": NaN, "131": NaN, "132": NaN, "133": NaN, "134": NaN, "135": NaN, "139": NaN}, "FTr": {"0": ".444", "1": ".067", "2": ".381", "3": ".542", "4": ".150", "7": ".131", "8": ".303", "9": ".412", "10": ".220", "11": ".154", "12": ".455", "13": ".485", "14": ".517", "15": ".536", "16": ".661", "17": ".396", "18": ".254", "19": ".444", "20": ".414", "21": ".557", "23": ".222", "24": ".676", "25": ".308", "26": "2.000", "27": ".716", "28": ".396", "29": ".517", "30": ".179", "33": ".214", "34": ".352", "35": ".864", "36": ".361", "37": ".468", "38": ".350", "39": NaN, "40": ".326", "41": ".350", "42": ".421", "43": ".352", "46": ".345", "48": ".398", "49": ".389", "50": ".326", "51": ".473", "54": ".303", "55": ".586", "56": ".469", "57": ".551", "58": "1.100", "59": ".362", "62": ".314", "63": ".438", "64": ".293", "65": ".432", "66": ".583", "67": ".000", "68": ".372", "69": ".790", "72": ".751", "73": ".700", "75": ".438", "76": ".430", "77": ".375", "78": ".471", "79": ".387", "80": ".528", "81": ".640", "82": ".308", "83": ".358", "84": ".288", "87": ".000", "88": ".286", "89": ".616", "90": "1.100", "93": "1.000", "94": ".485", "95": ".261", "96": ".545", "97": ".372", "98": ".667", "100": ".493", "101": ".292", "102": ".364", "103": ".470", "106": ".606", "107": ".430", "108": ".367", "109": ".445", "110": ".439", "111": ".558", "114": ".428", "115": ".428", "116": ".375", "117": ".183", "118": ".265", "119": ".471", "122": ".471", "123": ".451", "124": ".481", "125": ".467", "127": ".363", "128": ".234", "129": ".301", "130": ".526", "131": ".000", "132": ".513", "133": ".167", "134": ".417", "135": ".472", "139": ".426"}, "ORB%": {"0": NaN, "1": NaN, "2": NaN, "3": NaN, "4": NaN, "7": NaN, "8": NaN, "9": NaN, "10": NaN, "11": NaN, "12": NaN, "13": NaN, "14": NaN, "15": NaN, "16": NaN, "17": NaN, "18": NaN, "19": NaN, "20": NaN, "21": NaN, "23": NaN, "24": NaN, "25": NaN, "26": NaN, "27": NaN, "28": NaN, "29": NaN, "30": NaN, "33": NaN, "34": NaN, "35": NaN, "36": NaN, "37": NaN, "38": NaN, "39": NaN, "40": NaN, "41": NaN, "42": NaN, "43": NaN, "46": NaN, "48": NaN, "49": NaN, "50": NaN, "51": NaN, "54": NaN, "55": NaN, "56": NaN, "57": NaN, "58": NaN, "59": NaN, "62": NaN, "63": NaN, "64": NaN, "65": NaN, "66": NaN, "67": NaN, "68": NaN, "69": NaN, "72": NaN, "73": NaN, "75": NaN, "76": NaN, "77": NaN, "78": NaN, "79": NaN, "80": NaN, "81": NaN, "82": NaN, "83": NaN, "84": NaN, "87": NaN, "88": NaN, "89": NaN, "90": NaN, "93": NaN, "94": NaN, "95": NaN, "96": NaN, "97": NaN, "98": NaN, "100": NaN, "101": NaN, "102": NaN, "103": NaN, "106": NaN, "107": NaN, "108": NaN, "109": NaN, "110": NaN, "111": NaN, "114": NaN, "115": NaN, "116": NaN, "117": NaN, "118": NaN, "119": NaN, "122": NaN, "123": NaN, "124": NaN, "125": NaN, "127": NaN, "128": NaN, "129": NaN, "130": NaN, "131": NaN, "132": NaN, "133": NaN, "134": NaN, "135": NaN, "139": NaN}, "DRB%": {"0": NaN, "1": NaN, "2": NaN, "3": NaN, "4": NaN, "7": NaN, "8": NaN, "9": NaN, "10": NaN, "11": NaN, "12": NaN, "13": NaN, "14": NaN, "15": NaN, "16": NaN, "17": NaN, "18": NaN, "19": NaN, "20": NaN, "21": NaN, "23": NaN, "24": NaN, "25": NaN, "26": NaN, "27": NaN, "28": NaN, "29": NaN, "30": NaN, "33": NaN, "34": NaN, "35": NaN, "36": NaN, "37": NaN, "38": NaN, "39": NaN, "40": NaN, "41": NaN, "42": NaN, "43": NaN, "46": NaN, "48": NaN, "49": NaN, "50": NaN, "51": NaN, "54": NaN, "55": NaN, "56": NaN, "57": NaN, "58": NaN, "59": NaN, "62": NaN, "63": NaN, "64": NaN, "65": NaN, "66": NaN, "67": NaN, "68": NaN, "69": NaN, "72": NaN, "73": NaN, "75": NaN, "76": NaN, "77": NaN, "78": NaN, "79": NaN, "80": NaN, "81": NaN, "82": NaN, "83": NaN, "84": NaN, "87": NaN, "88": NaN, "89": NaN, "90": NaN, "93": NaN, "94": NaN, "95": NaN, "96": NaN, "97": NaN, "98": NaN, "100": NaN, "101": NaN, "102": NaN, "103": NaN, "106": NaN, "107": NaN, "108": NaN, "109": NaN, "110": NaN, "111": NaN, "114": NaN, "115": NaN, "116": NaN, "117": NaN, "118": NaN, "119": NaN, "122": NaN, "123": NaN, "124": NaN, "125": NaN, "127": NaN, "128": NaN, "129": NaN, "130": NaN, "131": NaN, "132": NaN, "133": NaN, "134": NaN, "135": NaN, "139": NaN}, "TRB%": {"0": NaN, "1": NaN, "2": NaN, "3": NaN, "4": NaN, "7": NaN, "8": NaN, "9": NaN, "10": NaN, "11": NaN, "12": NaN, "13": NaN, "14": NaN, "15": NaN, "16": NaN, "17": NaN, "18": NaN, "19": NaN, "20": NaN, "21": NaN, "23": NaN, "24": NaN, "25": NaN, "26": NaN, "27": NaN, "28": NaN, "29": NaN, "30": NaN, "33": NaN, "34": NaN, "35": NaN, "36": NaN, "37": NaN, "38": NaN, "39": NaN, "40": NaN, "41": NaN, "42": NaN, "43": NaN, "46": NaN, "48": NaN, "49": NaN, "50": NaN, "51": NaN, "54": NaN, "55": NaN, "56": NaN, "57": NaN, "58": NaN, "59": NaN, "62": NaN, "63": NaN, "64": NaN, "65": NaN, "66": NaN, "67": NaN, "68": NaN, "69": NaN, "72": NaN, "73": NaN, "75": NaN, "76": NaN, "77": NaN, "78": NaN, "79": NaN, "80": NaN, "81": NaN, "82": NaN, "83": NaN, "84": NaN, "87": NaN, "88": NaN, "89": NaN, "90": NaN, "93": NaN, "94": NaN, "95": NaN, "96": NaN, "97": NaN, "98": NaN, "100": NaN, "101": NaN, "102": NaN, "103": NaN, "106": NaN, "107": NaN, "108": NaN, "109": NaN, "110": NaN, "111": NaN, "114": NaN, "115": NaN, "116": NaN, "117": NaN, "118": NaN, "119": NaN, "122": NaN, "123": NaN, "124": NaN, "125": NaN, "127": NaN, "128": NaN, "129": NaN, "130": NaN, "131": NaN, "132": NaN, "133": NaN, "134": NaN, "135": NaN, "139": NaN}, "AST%": {"0": NaN, "1": NaN, "2": NaN, "3": NaN, "4": NaN, "7": NaN, "8": NaN, "9": NaN, "10": NaN, "11": NaN, "12": NaN, "13": NaN, "14": NaN, "15": NaN, "16": NaN, "17": NaN, "18": NaN, "19": NaN, "20": NaN, "21": NaN, "23": NaN, "24": NaN, "25": NaN, "26": NaN, "27": NaN, "28": NaN, "29": NaN, "30": NaN, "33": NaN, "34": NaN, "35": NaN, "36": NaN, "37": NaN, "38": NaN, "39": NaN, "40": NaN, "41": NaN, "42": NaN, "43": NaN, "46": NaN, "48": NaN, "49": NaN, "50": NaN, "51": NaN, "54": NaN, "55": NaN, "56": NaN, "57": NaN, "58": NaN, "59": NaN, "62": NaN, "63": NaN, "64": NaN, "65": NaN, "66": NaN, "67": NaN, "68": NaN, "69": NaN, "72": NaN, "73": NaN, "75": NaN, "76": NaN, "77": NaN, "78": NaN, "79": NaN, "80": NaN, "81": NaN, "82": NaN, "83": NaN, "84": NaN, "87": NaN, "88": NaN, "89": NaN, "90": NaN, "93": NaN, "94": NaN, "95": NaN, "96": NaN, "97": NaN, "98": NaN, "100": NaN, "101": NaN, "102": NaN, "103": NaN, "106": NaN, "107": NaN, "108": NaN, "109": NaN, "110": NaN, "111": NaN, "114": NaN, "115": NaN, "116": NaN, "117": NaN, "118": NaN, "119": NaN, "122": NaN, "123": NaN, "124": NaN, "125": NaN, "127": NaN, "128": NaN, "129": NaN, "130": NaN, "131": NaN, "132": NaN, "133": NaN, "134": NaN, "135": NaN, "139": NaN}, "STL%": {"0": NaN, "1": NaN, "2": NaN, "3": NaN, "4": NaN, "7": NaN, "8": NaN, "9": NaN, "10": NaN, "11": NaN, "12": NaN, "13": NaN, "14": NaN, "15": NaN, "16": NaN, "17": NaN, "18": NaN, "19": NaN, "20": NaN, "21": NaN, "23": NaN, "24": NaN, "25": NaN, "26": NaN, "27": NaN, "28": NaN, "29": NaN, "30": NaN, "33": NaN, "34": NaN, "35": NaN, "36": NaN, "37": NaN, "38": NaN, "39": NaN, "40": NaN, "41": NaN, "42": NaN, "43": NaN, "46": NaN, "48": NaN, "49": NaN, "50": NaN, "51": NaN, "54": NaN, "55": NaN, "56": NaN, "57": NaN, "58": NaN, "59": NaN, "62": NaN, "63": NaN, "64": NaN, "65": NaN, "66": NaN, "67": NaN, "68": NaN, "69": NaN, "72": NaN, "73": NaN, "75": NaN, "76": NaN, "77": NaN, "78": NaN, "79": NaN, "80": NaN, "81": NaN, "82": NaN, "83": NaN, "84": NaN, "87": NaN, "88": NaN, "89": NaN, "90": NaN, "93": NaN, "94": NaN, "95": NaN, "96": NaN, "97": NaN, "98": NaN, "100": NaN, "101": NaN, "102": NaN, "103": NaN, "106": NaN, "107": NaN, "108": NaN, "109": NaN, "110": NaN, "111": NaN, "114": NaN, "115": NaN, "116": NaN, "117": NaN, "118": NaN, "119": NaN, "122": NaN, "123": NaN, "124": NaN, "125": NaN, "127": NaN, "128": NaN, "129": NaN, "130": NaN, "131": NaN, "132": NaN, "133": NaN, "134": NaN, "135": NaN, "139": NaN}, "BLK%": {"0": NaN, "1": NaN, "2": NaN, "3": NaN, "4": NaN, "7": NaN, "8": NaN, "9": NaN, "10": NaN, "11": NaN, "12": NaN, "13": NaN, "14": NaN, "15": NaN, "16": NaN, "17": NaN, "18": NaN, "19": NaN, "20": NaN, "21": NaN, "23": NaN, "24": NaN, "25": NaN, "26": NaN, "27": NaN, "28": NaN, "29": NaN, "30": NaN, "33": NaN, "34": NaN, "35": NaN, "36": NaN, "37": NaN, "38": NaN, "39": NaN, "40": NaN, "41": NaN, "42": NaN, "43": NaN, "46": NaN, "48": NaN, "49": NaN, "50": NaN, "51": NaN, "54": NaN, "55": NaN, "56": NaN, "57": NaN, "58": NaN, "59": NaN, "62": NaN, "63": NaN, "64": NaN, "65": NaN, "66": NaN, "67": NaN, "68": NaN, "69": NaN, "72": NaN, "73": NaN, "75": NaN, "76": NaN, "77": NaN, "78": NaN, "79": NaN, "80": NaN, "81": NaN, "82": NaN, "83": NaN, "84": NaN, "87": NaN, "88": NaN, "89": NaN, "90": NaN, "93": NaN, "94": NaN, "95": NaN, "96": NaN, "97": NaN, "98": NaN, "100": NaN, "101": NaN, "102": NaN, "103": NaN, "106": NaN, "107": NaN, "108": NaN, "109": NaN, "110": NaN, "111": NaN, "114": NaN, "115": NaN, "116": NaN, "117": NaN, "118": NaN, "119": NaN, "122": NaN, "123": NaN, "124": NaN, "125": NaN, "127": NaN, "128": NaN, "129": NaN, "130": NaN, "131": NaN, "132": NaN, "133": NaN, "134": NaN, "135": NaN, "139": NaN}, "TOV%": {"0": NaN, "1": NaN, "2": NaN, "3": NaN, "4": NaN, "7": NaN, "8": NaN, "9": NaN, "10": NaN, "11": NaN, "12": NaN, "13": NaN, "14": NaN, "15": NaN, "16": NaN, "17": NaN, "18": NaN, "19": NaN, "20": NaN, "21": NaN, "23": NaN, "24": NaN, "25": NaN, "26": NaN, "27": NaN, "28": NaN, "29": NaN, "30": NaN, "33": NaN, "34": NaN, "35": NaN, "36": NaN, "37": NaN, "38": NaN, "39": NaN, "40": NaN, "41": NaN, "42": NaN, "43": NaN, "46": NaN, "48": NaN, "49": NaN, "50": NaN, "51": NaN, "54": NaN, "55": NaN, "56": NaN, "57": NaN, "58": NaN, "59": NaN, "62": NaN, "63": NaN, "64": NaN, "65": NaN, "66": NaN, "67": NaN, "68": NaN, "69": NaN, "72": NaN, "73": NaN, "75": NaN, "76": NaN, "77": NaN, "78": NaN, "79": NaN, "80": NaN, "81": NaN, "82": NaN, "83": NaN, "84": NaN, "87": NaN, "88": NaN, "89": NaN, "90": NaN, "93": NaN, "94": NaN, "95": NaN, "96": NaN, "97": NaN, "98": NaN, "100": NaN, "101": NaN, "102": NaN, "103": NaN, "106": NaN, "107": NaN, "108": NaN, "109": NaN, "110": NaN, "111": NaN, "114": NaN, "115": NaN, "116": NaN, "117": NaN, "118": NaN, "119": NaN, "122": NaN, "123": NaN, "124": NaN, "125": NaN, "127": NaN, "128": NaN, "129": NaN, "130": NaN, "131": NaN, "132": NaN, "133": NaN, "134": NaN, "135": NaN, "139": NaN}, "USG%": {"0": NaN, "1": NaN, "2": NaN, "3": NaN, "4": NaN, "7": NaN, "8": NaN, "9": NaN, "10": NaN, "11": NaN, "12": NaN, "13": NaN, "14": NaN, "15": NaN, "16": NaN, "17": NaN, "18": NaN, "19": NaN, "20": NaN, "21": NaN, "23": NaN, "24": NaN, "25": NaN, "26": NaN, "27": NaN, "28": NaN, "29": NaN, "30": NaN, "33": NaN, "34": NaN, "35": NaN, "36": NaN, "37": NaN, "38": NaN, "39": NaN, "40": NaN, "41": NaN, "42": NaN, "43": NaN, "46": NaN, "48": NaN, "49": NaN, "50": NaN, "51": NaN, "54": NaN, "55": NaN, "56": NaN, "57": NaN, "58": NaN, "59": NaN, "62": NaN, "63": NaN, "64": NaN, "65": NaN, "66": NaN, "67": NaN, "68": NaN, "69": NaN, "72": NaN, "73": NaN, "75": NaN, "76": NaN, "77": NaN, "78": NaN, "79": NaN, "80": NaN, "81": NaN, "82": NaN, "83": NaN, "84": NaN, "87": NaN, "88": NaN, "89": NaN, "90": NaN, "93": NaN, "94": NaN, "95": NaN, "96": NaN, "97": NaN, "98": NaN, "100": NaN, "101": NaN, "102": NaN, "103": NaN, "106": NaN, "107": NaN, "108": NaN, "109": NaN, "110": NaN, "111": NaN, "114": NaN, "115": NaN, "116": NaN, "117": NaN, "118": NaN, "119": NaN, "122": NaN, "123": NaN, "124": NaN, "125": NaN, "127": NaN, "128": NaN, "129": NaN, "130": NaN, "131": NaN, "132": NaN, "133": NaN, "134": NaN, "135": NaN, "139": NaN}, "OWS": {"0": "-0.7", "1": "-0.3", "2": "1.2", "3": "1.5", "4": NaN, "7": "-1.1", "8": "-0.7", "9": "0.8", "10": "0.1", "11": "-1.6", "12": "-1.1", "13": "7.2", "14": "2.0", "15": "2.2", "16": "-0.1", "17": "0.7", "18": "1.4", "19": "-0.7", "20": "6.5", "21": "4.4", "23": "-0.5", "24": "2.7", "25": "-0.3", "26": "0.0", "27": "7.6", "28": "0.2", "29": "6.5", "30": "-2.0", "33": "-2.2", "34": "1.2", "35": "9.0", "36": "-0.3", "37": "-0.1", "38": "-0.2", "39": "0.0", "40": "-0.7", "41": "0.2", "42": "0.8", "43": "-1.5", "46": "0.3", "48": "0.2", "49": "-1.3", "50": "-0.5", "51": "2.0", "54": "2.5", "55": "15.4", "56": "2.1", "57": "2.7", "58": "0.0", "59": "1.0", "62": "1.2", "63": "-0.3", "64": "2.5", "65": "-0.1", "66": "13.1", "67": "-0.1", "68": "2.9", "69": "0.6", "72": "-0.5", "73": "4.6", "75": "1.8", "76": "1.0", "77": "-0.1", "78": "6.1", "79": "2.2", "80": "4.2", "81": "2.5", "82": "-1.2", "83": "-1.6", "84": NaN, "87": "0.0", "88": "-0.2", "89": "0.3", "90": "0.1", "93": "-0.2", "94": "4.2", "95": "1.3", "96": "2.8", "97": "-0.6", "98": "0.3", "100": "3.0", "101": "0.3", "102": "0.6", "103": "2.6", "106": "8.4", "107": "1.2", "108": "0.0", "109": "0.0", "110": "5.0", "111": "2.5", "114": "9.4", "115": "1.0", "116": "-0.2", "117": "1.3", "118": "-0.4", "119": "-0.1", "122": "2.1", "123": "1.3", "124": "0.2", "125": "-1.3", "127": "-2.0", "128": "0.1", "129": "0.2", "130": "1.5", "131": "-0.1", "132": "5.1", "133": "0.1", "134": "3.4", "135": "2.5", "139": "2.6"}, "DWS": {"0": "0.1", "1": "0.0", "2": "0.9", "3": "0.8", "4": NaN, "7": "0.3", "8": "0.3", "9": "1.2", "10": "0.1", "11": "0.7", "12": "1.1", "13": "1.3", "14": "0.8", "15": "1.9", "16": "3.0", "17": "1.7", "18": "4.4", "19": "0.7", "20": "1.6", "21": "3.3", "23": "1.4", "24": "0.8", "25": "0.1", "26": "0.0", "27": "1.0", "28": "1.4", "29": "3.9", "30": "0.3", "33": "0.4", "34": "1.8", "35": "2.8", "36": "2.2", "37": "0.3", "38": "2.5", "39": "0.0", "40": "2.8", "41": "0.4", "42": "1.1", "43": "1.5", "46": "2.9", "48": "0.9", "49": "1.8", "50": "0.5", "51": "0.7", "54": "3.4", "55": "3.0", "56": "2.4", "57": "3.6", "58": "0.1", "59": "2.3", "62": "4.0", "63": "0.3", "64": "2.7", "65": "0.1", "66": "1.5", "67": "0.0", "68": "3.2", "69": "0.3", "72": "0.6", "73": "1.7", "75": "2.9", "76": "1.7", "77": "0.0", "78": "6.6", "79": "4.4", "80": "0.6", "81": "1.0", "82": "0.5", "83": "1.7", "84": NaN, "87": "0.0", "88": "0.0", "89": "4.0", "90": "0.0", "93": "0.0", "94": "2.9", "95": "4.5", "96": "2.4", "97": "0.1", "98": "0.0", "100": "4.8", "101": "0.5", "102": "2.2", "103": "1.1", "106": "6.3", "107": "1.6", "108": "1.2", "109": "0.5", "110": "4.3", "111": "2.2", "114": "1.0", "115": "1.5", "116": "0.0", "117": "2.8", "118": "0.1", "119": "0.2", "122": "2.6", "123": "1.7", "124": "0.3", "125": "0.9", "127": "1.5", "128": "0.1", "129": "0.1", "130": "1.5", "131": "0.0", "132": "4.0", "133": "0.0", "134": "1.8", "135": "1.2", "139": "1.3"}, "WS": {"0": "-0.6", "1": "-0.3", "2": "2.1", "3": "2.3", "4": NaN, "7": "-0.8", "8": "-0.4", "9": "2.0", "10": "0.2", "11": "-1.0", "12": "0.0", "13": "8.6", "14": "2.7", "15": "4.1", "16": "2.9", "17": "2.4", "18": "5.8", "19": "0.0", "20": "8.1", "21": "7.7", "23": "0.9", "24": "3.5", "25": "-0.3", "26": "0.0", "27": "8.6", "28": "1.7", "29": "10.4", "30": "-1.7", "33": "-1.8", "34": "2.9", "35": "11.8", "36": "1.8", "37": "0.2", "38": "2.3", "39": "0.0", "40": "2.1", "41": "0.6", "42": "1.9", "43": "0.0", "46": "3.3", "48": "1.1", "49": "0.6", "50": "0.1", "51": "2.8", "54": "5.8", "55": "18.3", "56": "4.5", "57": "6.3", "58": "0.2", "59": "3.4", "62": "5.2", "63": "0.1", "64": "5.2", "65": "0.0", "66": "14.6", "67": "-0.1", "68": "6.1", "69": "0.9", "72": "0.1", "73": "6.3", "75": "4.7", "76": "2.6", "77": "0.0", "78": "12.7", "79": "6.6", "80": "4.9", "81": "3.6", "82": "-0.7", "83": "0.1", "84": NaN, "87": "0.0", "88": "-0.2", "89": "4.3", "90": "0.2", "93": "-0.1", "94": "7.1", "95": "5.7", "96": "5.2", "97": "-0.6", "98": "0.3", "100": "7.8", "101": "0.7", "102": "2.8", "103": "3.7", "106": "14.8", "107": "2.8", "108": "1.2", "109": "0.5", "110": "9.3", "111": "4.7", "114": "10.4", "115": "2.5", "116": "-0.1", "117": "4.1", "118": "-0.3", "119": "0.1", "122": "4.7", "123": "3.0", "124": "0.6", "125": "-0.4", "127": "-0.6", "128": "0.1", "129": "0.3", "130": "3.1", "131": "-0.1", "132": "9.1", "133": "0.1", "134": "5.3", "135": "3.7", "139": "3.9"}, "WS/48": {"0": "-0.123", "1": "-0.279", "2": ".062", "3": ".082", "4": NaN, "7": "-0.058", "8": "-0.051", "9": ".063", "10": ".039", "11": "-0.031", "12": ".000", "13": ".173", "14": ".135", "15": ".082", "16": ".084", "17": ".054", "18": ".117", "19": "-0.001", "20": ".137", "21": ".172", "23": ".028", "24": ".115", "25": "-0.138", "26": ".193", "27": ".155", "28": ".052", "29": ".186", "30": "-0.065", "33": "-0.171", "34": ".116", "35": ".210", "36": ".034", "37": ".044", "38": ".040", "39": ".010", "40": ".058", "41": ".018", "42": ".048", "43": "-0.001", "46": ".064", "48": ".020", "49": ".024", "50": ".004", "51": ".067", "54": ".096", "55": ".267", "56": ".152", "57": ".129", "58": ".183", "59": ".126", "62": ".113", "63": ".007", "64": ".200", "65": ".002", "66": ".252", "67": "-0.241", "68": ".118", "69": ".231", "72": ".006", "73": ".129", "75": ".118", "76": ".086", "77": "-0.023", "78": ".258", "79": ".141", "80": ".141", "81": ".179", "82": "-0.065", "83": ".007", "84": NaN, "87": "-0.724", "88": "-0.344", "89": ".096", "90": ".138", "93": "-0.187", "94": ".125", "95": ".111", "96": ".116", "97": "-0.184", "98": ".802", "100": ".157", "101": ".018", "102": ".075", "103": ".118", "106": ".267", "107": ".129", "108": ".035", "109": ".032", "110": ".164", "111": ".143", "114": ".202", "115": ".059", "116": "-0.216", "117": ".106", "118": "-0.105", "119": ".006", "122": ".137", "123": ".065", "124": ".075", "125": "-0.034", "127": "-0.014", "128": ".026", "129": ".055", "130": ".071", "131": "-0.165", "132": ".172", "133": ".047", "134": ".170", "135": ".095", "139": ".105"}, "OBPM": {"0": NaN, "1": NaN, "2": NaN, "3": NaN, "4": NaN, "7": NaN, "8": NaN, "9": NaN, "10": NaN, "11": NaN, "12": NaN, "13": NaN, "14": NaN, "15": NaN, "16": NaN, "17": NaN, "18": NaN, "19": NaN, "20": NaN, "21": NaN, "23": NaN, "24": NaN, "25": NaN, "26": NaN, "27": NaN, "28": NaN, "29": NaN, "30": NaN, "33": NaN, "34": NaN, "35": NaN, "36": NaN, "37": NaN, "38": NaN, "39": NaN, "40": NaN, "41": NaN, "42": NaN, "43": NaN, "46": NaN, "48": NaN, "49": NaN, "50": NaN, "51": NaN, "54": NaN, "55": NaN, "56": NaN, "57": NaN, "58": NaN, "59": NaN, "62": NaN, "63": NaN, "64": NaN, "65": NaN, "66": NaN, "67": NaN, "68": NaN, "69": NaN, "72": NaN, "73": NaN, "75": NaN, "76": NaN, "77": NaN, "78": NaN, "79": NaN, "80": NaN, "81": NaN, "82": NaN, "83": NaN, "84": NaN, "87": NaN, "88": NaN, "89": NaN, "90": NaN, "93": NaN, "94": NaN, "95": NaN, "96": NaN, "97": NaN, "98": NaN, "100": NaN, "101": NaN, "102": NaN, "103": NaN, "106": NaN, "107": NaN, "108": NaN, "109": NaN, "110": NaN, "111": NaN, "114": NaN, "115": NaN, "116": NaN, "117": NaN, "118": NaN, "119": NaN, "122": NaN, "123": NaN, "124": NaN, "125": NaN, "127": NaN, "128": NaN, "129": NaN, "130": NaN, "131": NaN, "132": NaN, "133": NaN, "134": NaN, "135": NaN, "139": NaN}, "DBPM": {"0": NaN, "1": NaN, "2": NaN, "3": NaN, "4": NaN, "7": NaN, "8": NaN, "9": NaN, "10": NaN, "11": NaN, "12": NaN, "13": NaN, "14": NaN, "15": NaN, "16": NaN, "17": NaN, "18": NaN, "19": NaN, "20": NaN, "21": NaN, "23": NaN, "24": NaN, "25": NaN, "26": NaN, "27": NaN, "28": NaN, "29": NaN, "30": NaN, "33": NaN, "34": NaN, "35": NaN, "36": NaN, "37": NaN, "38": NaN, "39": NaN, "40": NaN, "41": NaN, "42": NaN, "43": NaN, "46": NaN, "48": NaN, "49": NaN, "50": NaN, "51": NaN, "54": NaN, "55": NaN, "56": NaN, "57": NaN, "58": NaN, "59": NaN, "62": NaN, "63": NaN, "64": NaN, "65": NaN, "66": NaN, "67": NaN, "68": NaN, "69": NaN, "72": NaN, "73": NaN, "75": NaN, "76": NaN, "77": NaN, "78": NaN, "79": NaN, "80": NaN, "81": NaN, "82": NaN, "83": NaN, "84": NaN, "87": NaN, "88": NaN, "89": NaN, "90": NaN, "93": NaN, "94": NaN, "95": NaN, "96": NaN, "97": NaN, "98": NaN, "100": NaN, "101": NaN, "102": NaN, "103": NaN, "106": NaN, "107": NaN, "108": NaN, "109": NaN, "110": NaN, "111": NaN, "114": NaN, "115": NaN, "116": NaN, "117": NaN, "118": NaN, "119": NaN, "122": NaN, "123": NaN, "124": NaN, "125": NaN, "127": NaN, "128": NaN, "129": NaN, "130": NaN, "131": NaN, "132": NaN, "133": NaN, "134": NaN, "135": NaN, "139": NaN}, "BPM": {"0": NaN, "1": NaN, "2": NaN, "3": NaN, "4": NaN, "7": NaN, "8": NaN, "9": NaN, "10": NaN, "11": NaN, "12": NaN, "13": NaN, "14": NaN, "15": NaN, "16": NaN, "17": NaN, "18": NaN, "19": NaN, "20": NaN, "21": NaN, "23": NaN, "24": NaN, "25": NaN, "26": NaN, "27": NaN, "28": NaN, "29": NaN, "30": NaN, "33": NaN, "34": NaN, "35": NaN, "36": NaN, "37": NaN, "38": NaN, "39": NaN, "40": NaN, "41": NaN, "42": NaN, "43": NaN, "46": NaN, "48": NaN, "49": NaN, "50": NaN, "51": NaN, "54": NaN, "55": NaN, "56": NaN, "57": NaN, "58": NaN, "59": NaN, "62": NaN, "63": NaN, "64": NaN, "65": NaN, "66": NaN, "67": NaN, "68": NaN, "69": NaN, "72": NaN, "73": NaN, "75": NaN, "76": NaN, "77": NaN, "78": NaN, "79": NaN, "80": NaN, "81": NaN, "82": NaN, "83": NaN, "84": NaN, "87": NaN, "88": NaN, "89": NaN, "90": NaN, "93": NaN, "94": NaN, "95": NaN, "96": NaN, "97": NaN, "98": NaN, "100": NaN, "101": NaN, "102": NaN, "103": NaN, "106": NaN, "107": NaN, "108": NaN, "109": NaN, "110": NaN, "111": NaN, "114": NaN, "115": NaN, "116": NaN, "117": NaN, "118": NaN, "119": NaN, "122": NaN, "123": NaN, "124": NaN, "125": NaN, "127": NaN, "128": NaN, "129": NaN, "130": NaN, "131": NaN, "132": NaN, "133": NaN, "134": NaN, "135": NaN, "139": NaN}, "VORP": {"0": NaN, "1": NaN, "2": NaN, "3": NaN, "4": NaN, "7": NaN, "8": NaN, "9": NaN, "10": NaN, "11": NaN, "12": NaN, "13": NaN, "14": NaN, "15": NaN, "16": NaN, "17": NaN, "18": NaN, "19": NaN, "20": NaN, "21": NaN, "23": NaN, "24": NaN, "25": NaN, "26": NaN, "27": NaN, "28": NaN, "29": NaN, "30": NaN, "33": NaN, "34": NaN, "35": NaN, "36": NaN, "37": NaN, "38": NaN, "39": NaN, "40": NaN, "41": NaN, "42": NaN, "43": NaN, "46": NaN, "48": NaN, "49": NaN, "50": NaN, "51": NaN, "54": NaN, "55": NaN, "56": NaN, "57": NaN, "58": NaN, "59": NaN, "62": NaN, "63": NaN, "64": NaN, "65": NaN, "66": NaN, "67": NaN, "68": NaN, "69": NaN, "72": NaN, "73": NaN, "75": NaN, "76": NaN, "77": NaN, "78": NaN, "79": NaN, "80": NaN, "81": NaN, "82": NaN, "83": NaN, "84": NaN, "87": NaN, "88": NaN, "89": NaN, "90": NaN, "93": NaN, "94": NaN, "95": NaN, "96": NaN, "97": NaN, "98": NaN, "100": NaN, "101": NaN, "102": NaN, "103": NaN, "106": NaN, "107": NaN, "108": NaN, "109": NaN, "110": NaN, "111": NaN, "114": NaN, "115": NaN, "116": NaN, "117": NaN, "118": NaN, "119": NaN, "122": NaN, "123": NaN, "124": NaN, "125": NaN, "127": NaN, "128": NaN, "129": NaN, "130": NaN, "131": NaN, "132": NaN, "133": NaN, "134": NaN, "135": NaN, "139": NaN}}