{"Player": {"0": "LeBron James", "1": "Kevin Durant", "2": "Kobe Bryant", "3": "Dwight Howard", "4": "Dwyane Wade", "5": "Carmelo Anthony", "6": "Dirk Nowitzki", "7": "Deron Williams", "8": "Amar'e Stoudemire", "9": "Manu Gin\u00f3bili", "10": "Chauncey Billups", "11": "Chris Bosh", "12": "Stephen Jackson", "13": "Joe Johnson"}, "Pos": {"0": "SF", "1": "SF", "2": "SG", "3": "C", "4": "SG", "5": "SF", "6": "PF", "7": "PG", "8": "PF", "9": "SG", "10": "PG", "11": "C", "12": "SF", "13": "SG"}, "Age": {"0": 24, "1": 20, "2": 30, "3": 23, "4": 27, "5": 24, "6": 30, "7": 24, "8": 26, "9": 31, "10": 32, "11": 24, "12": 30, "13": 27}, "Tm": {"0": "CLE", "1": "OKC", "2": "LAL", "3": "ORL", "4": "MIA", "5": "DEN", "6": "DAL", "7": "UTA", "8": "PHO", "9": "SAS", "10": "TOT", "11": "TOR", "12": "GSW", "13": "ATL"}, "G": {"0": 81.0, "1": 74.0, "2": 82.0, "3": 79.0, "4": 79.0, "5": 66.0, "6": 81.0, "7": 68.0, "8": 53.0, "9": 44.0, "10": 79.0, "11": 77.0, "12": 59.0, "13": 79.0}, "GS": {"0": 81.0, "1": 74.0, "2": 82.0, "3": 79.0, "4": 79.0, "5": 66.0, "6": 81.0, "7": 68.0, "8": 53.0, "9": 7.0, "10": 79.0, "11": 77.0, "12": 59.0, "13": 79.0}, "MP": {"0": 37.7, "1": 39.0, "2": 36.1, "3": 35.7, "4": 38.6, "5": 34.5, "6": 37.7, "7": 36.8, "8": 36.8, "9": 26.8, "10": 35.3, "11": 38.0, "12": 39.6, "13": 39.5}, "FG": {"0": 9.7, "1": 8.9, "2": 9.8, "3": 7.1, "4": 10.8, "5": 8.1, "6": 9.6, "7": 6.8, "8": 7.6, "9": 5.1, "10": 5.2, "11": 8.0, "12": 7.0, "13": 7.8}, "FGA": {"0": 19.9, "1": 18.8, "2": 20.9, "3": 12.4, "4": 22.0, "5": 18.3, "6": 20.0, "7": 14.5, "8": 14.1, "9": 11.2, "10": 12.4, "11": 16.4, "12": 16.9, "13": 18.0}, "FG%": {"0": 0.489, "1": 0.476, "2": 0.467, "3": 0.572, "4": 0.491, "5": 0.443, "6": 0.479, "7": 0.471, "8": 0.539, "9": 0.454, "10": 0.418, "11": 0.487, "12": 0.414, "13": 0.437}, "3P": {"0": 1.6, "1": 1.3, "2": 1.4, "3": 0.0, "4": 1.1, "5": 1.0, "6": 0.8, "7": 1.0, "8": 0.1, "9": 1.6, "10": 2.1, "11": 0.2, "12": 1.7, "13": 1.9}, "3PA": {"0": 4.7, "1": 3.1, "2": 4.1, "3": 0.0, "4": 3.5, "5": 2.6, "6": 2.1, "7": 3.3, "8": 0.1, "9": 4.8, "10": 5.0, "11": 0.6, "12": 5.2, "13": 5.2}, "3P%": {"0": 0.344, "1": 0.422, "2": 0.351, "3": 0.0, "4": 0.317, "5": 0.371, "6": 0.359, "7": 0.31, "8": 0.429, "9": 0.33, "10": 0.408, "11": 0.245, "12": 0.338, "13": 0.36}, "2P": {"0": 8.1, "1": 7.6, "2": 8.3, "3": 7.1, "4": 9.7, "5": 7.2, "6": 8.8, "7": 5.8, "8": 7.6, "9": 3.5, "10": 3.1, "11": 7.8, "12": 5.3, "13": 6.0}, "2PA": {"0": 15.2, "1": 15.7, "2": 16.8, "3": 12.4, "4": 18.5, "5": 15.7, "6": 17.9, "7": 11.1, "8": 14.0, "9": 6.4, "10": 7.4, "11": 15.8, "12": 11.7, "13": 12.7}, "2P%": {"0": 0.535, "1": 0.486, "2": 0.496, "3": 0.573, "4": 0.524, "5": 0.455, "6": 0.493, "7": 0.518, "8": 0.54, "9": 0.546, "10": 0.425, "11": 0.497, "12": 0.448, "13": 0.468}, "eFG%": {"0": 0.53, "1": 0.51, "2": 0.502, "3": 0.572, "4": 0.516, "5": 0.469, "6": 0.498, "7": 0.506, "8": 0.541, "9": 0.524, "10": 0.501, "11": 0.492, "12": 0.466, "13": 0.489}, "FT": {"0": 7.3, "1": 6.1, "2": 5.9, "3": 6.4, "4": 7.5, "5": 5.6, "6": 6.0, "7": 4.8, "8": 6.1, "9": 3.8, "10": 5.3, "11": 6.5, "12": 5.0, "13": 3.8}, "FTA": {"0": 9.4, "1": 7.1, "2": 6.9, "3": 10.7, "4": 9.8, "5": 7.1, "6": 6.7, "7": 5.6, "8": 7.3, "9": 4.3, "10": 5.8, "11": 8.0, "12": 6.0, "13": 4.6}, "FT%": {"0": 0.78, "1": 0.863, "2": 0.856, "3": 0.594, "4": 0.765, "5": 0.793, "6": 0.89, "7": 0.849, "8": 0.835, "9": 0.884, "10": 0.913, "11": 0.817, "12": 0.826, "13": 0.826}, "ORB": {"0": 1.3, "1": 1.0, "2": 1.1, "3": 4.3, "4": 1.1, "5": 1.6, "6": 1.1, "7": 0.4, "8": 2.2, "9": 0.5, "10": 0.4, "11": 2.8, "12": 1.2, "13": 0.8}, "DRB": {"0": 6.3, "1": 5.5, "2": 4.1, "3": 9.6, "4": 3.9, "5": 5.2, "6": 7.3, "7": 2.5, "8": 5.9, "9": 4.0, "10": 2.6, "11": 7.2, "12": 3.9, "13": 3.6}, "TRB": {"0": 7.6, "1": 6.5, "2": 5.2, "3": 13.8, "4": 5.0, "5": 6.8, "6": 8.4, "7": 2.9, "8": 8.1, "9": 4.5, "10": 3.0, "11": 10.0, "12": 5.1, "13": 4.4}, "AST": {"0": 7.2, "1": 2.8, "2": 4.9, "3": 1.4, "4": 7.5, "5": 3.4, "6": 2.4, "7": 10.7, "8": 2.0, "9": 3.6, "10": 6.4, "11": 2.5, "12": 6.5, "13": 5.8}, "STL": {"0": 1.7, "1": 1.3, "2": 1.5, "3": 1.0, "4": 2.2, "5": 1.1, "6": 0.8, "7": 1.1, "8": 0.9, "9": 1.5, "10": 1.2, "11": 0.9, "12": 1.5, "13": 1.1}, "BLK": {"0": 1.1, "1": 0.7, "2": 0.5, "3": 2.9, "4": 1.3, "5": 0.4, "6": 0.8, "7": 0.3, "8": 1.1, "9": 0.4, "10": 0.2, "11": 1.0, "12": 0.5, "13": 0.2}, "TOV": {"0": 3.0, "1": 3.0, "2": 2.6, "3": 3.0, "4": 3.4, "5": 3.0, "6": 1.9, "7": 3.4, "8": 2.8, "9": 2.0, "10": 2.2, "11": 2.3, "12": 3.9, "13": 2.5}, "PF": {"0": 1.7, "1": 1.8, "2": 2.3, "3": 3.4, "4": 2.3, "5": 3.0, "6": 2.2, "7": 2.0, "8": 3.1, "9": 2.0, "10": 2.0, "11": 2.5, "12": 2.6, "13": 2.2}, "PTS": {"0": 28.4, "1": 25.3, "2": 26.8, "3": 20.6, "4": 30.2, "5": 22.8, "6": 25.9, "7": 19.4, "8": 21.4, "9": 15.5, "10": 17.7, "11": 22.7, "12": 20.7, "13": 21.4}, "PER": {"0": 31.7, "1": 20.8, "2": 24.4, "3": 25.4, "4": 30.4, "5": 19.0, "6": 23.1, "7": 21.1, "8": 20.3, "9": 22.9, "10": 18.8, "11": 22.1, "12": 16.1, "13": 18.2}, "TS%": {"0": 0.591, "1": 0.577, "2": 0.561, "3": 0.6, "4": 0.574, "5": 0.532, "6": 0.564, "7": 0.573, "8": 0.617, "9": 0.594, "10": 0.592, "11": 0.569, "12": 0.53, "13": 0.534}, "3PAr": {"0": 0.238, "1": 0.165, "2": 0.196, "3": 0.002, "4": 0.16, "5": 0.141, "6": 0.105, "7": 0.23, "8": 0.009, "9": 0.426, "10": 0.405, "11": 0.039, "12": 0.306, "13": 0.292}, "FTr": {"0": 0.472, "1": 0.377, "2": 0.329, "3": 0.867, "4": 0.443, "5": 0.388, "6": 0.337, "7": 0.39, "8": 0.517, "9": 0.387, "10": 0.467, "11": 0.489, "12": 0.357, "13": 0.255}, "ORB%": {"0": 4.3, "1": 3.0, "2": 3.5, "3": 13.8, "4": 3.5, "5": 5.6, "6": 3.3, "7": 1.1, "8": 7.2, "9": 2.5, "10": 1.4, "11": 8.7, "12": 3.3, "13": 2.4}, "DRB%": {"0": 19.0, "1": 16.4, "2": 12.8, "3": 29.5, "4": 12.2, "5": 17.0, "6": 22.1, "7": 8.1, "8": 18.1, "9": 17.3, "10": 8.4, "11": 22.1, "12": 10.8, "13": 10.5}, "TRB%": {"0": 11.9, "1": 9.6, "2": 8.2, "3": 21.8, "4": 7.8, "5": 11.5, "6": 12.8, "7": 4.6, "8": 12.9, "9": 10.0, "10": 5.0, "11": 15.5, "12": 7.1, "13": 6.5}, "AST%": {"0": 38.0, "1": 13.5, "2": 23.8, "3": 7.3, "4": 40.3, "5": 18.1, "6": 12.1, "7": 47.8, "8": 8.3, "9": 23.1, "10": 28.9, "11": 11.6, "12": 25.6, "13": 26.4}, "STL%": {"0": 2.4, "1": 1.7, "2": 2.1, "3": 1.4, "4": 3.0, "5": 1.7, "6": 1.0, "7": 1.5, "8": 1.3, "9": 2.9, "10": 1.7, "11": 1.2, "12": 1.8, "13": 1.4}, "BLK%": {"0": 2.4, "1": 1.4, "2": 1.0, "3": 5.9, "4": 2.8, "5": 0.8, "6": 1.5, "7": 0.6, "8": 2.1, "9": 1.0, "10": 0.5, "11": 2.0, "12": 0.9, "13": 0.5}, "TOV%": {"0": 11.0, "1": 12.2, "2": 9.7, "3": 15.1, "4": 11.6, "5": 12.3, "6": 7.8, "7": 16.5, "8": 14.0, "9": 13.3, "10": 13.0, "11": 10.2, "12": 16.6, "13": 11.0}, "USG%": {"0": 33.8, "1": 28.3, "2": 32.2, "3": 26.1, "4": 36.2, "5": 31.5, "6": 30.3, "7": 24.7, "8": 24.2, "9": 27.2, "10": 21.7, "11": 26.9, "12": 25.2, "13": 26.6}, "OWS": {"0": 13.7, "1": 5.2, "2": 8.6, "3": 6.2, "4": 10.3, "5": 2.4, "6": 7.5, "7": 6.5, "8": 4.6, "9": 2.7, "10": 7.9, "11": 6.6, "12": 1.5, "13": 5.1}, "DWS": {"0": 6.5, "1": 2.7, "2": 4.0, "3": 7.6, "4": 4.4, "5": 2.6, "6": 3.4, "7": 1.9, "8": 1.4, "9": 2.3, "10": 2.2, "11": 3.1, "12": 0.7, "13": 2.5}, "WS": {"0": 20.3, "1": 7.9, "2": 12.7, "3": 13.8, "4": 14.7, "5": 5.0, "6": 10.9, "7": 8.4, "8": 6.1, "9": 5.0, "10": 10.1, "11": 9.7, "12": 2.2, "13": 7.6}, "WS/48": {"0": 0.318, "1": 0.132, "2": 0.206, "3": 0.234, "4": 0.232, "5": 0.105, "6": 0.171, "7": 0.16, "8": 0.149, "9": 0.203, "10": 0.174, "11": 0.159, "12": 0.045, "13": 0.116}, "OBPM": {"0": 9.4, "1": 2.2, "2": 4.8, "3": 0.1, "4": 8.7, "5": 0.8, "6": 1.9, "7": 4.3, "8": 1.3, "9": 4.2, "10": 4.2, "11": 2.0, "12": 1.7, "13": 2.9}, "DBPM": {"0": 3.6, "1": -0.5, "2": -0.2, "3": 4.3, "4": 2.0, "5": -0.5, "6": -0.7, "7": -2.5, "8": -0.3, "9": 1.8, "10": -1.7, "11": 0.5, "12": -1.5, "13": -1.2}, "BPM": {"0": 13.0, "1": 1.8, "2": 4.5, "3": 4.4, "4": 10.7, "5": 0.3, "6": 1.2, "7": 1.8, "8": 1.0, "9": 6.0, "10": 2.5, "11": 2.4, "12": 0.2, "13": 1.7}, "VORP": {"0": 11.6, "1": 2.8, "2": 4.9, "3": 4.6, "4": 9.7, "5": 1.3, "6": 2.4, "7": 2.4, "8": 1.5, "9": 2.4, "10": 3.2, "11": 3.3, "12": 1.3, "13": 3.0}, "Share": {"0": 0.98, "1": 0.495, "2": 0.48700000000000004, "3": 0.389, "4": 0.09699999999999999, "5": 0.053, "6": 0.045, "7": 0.006, "8": 0.004, "9": 0.002, "10": 0.001, "11": 0.001, "12": 0.001, "13": 0.001}}